wfdload/__init__.py
wfdload/chordsplit.py
wfdload/label.py
wfdload/loader.py
wfdload/wfd.py
wfdload-0.0.5.6.dist-info/LICENSE
wfdload-0.0.5.6.dist-info/METADATA
wfdload-0.0.5.6.dist-info/WHEEL
wfdload-0.0.5.6.dist-info/top_level.txt
wfdload-0.0.5.6.dist-info/RECORD
