Metadata-Version: 2.1
Name: wfdload
Version: 0.0.5.6
Summary: A library to handle wfd in python.
Home-page: https://github.com/anime-song/wfdload
Author: anime-song
Author-email: UNKNOWN
License: MIT
Platform: UNKNOWN
Requires-Dist: numpy
Requires-Dist: pandas
